{"_path":"/guide/how-does-it-work","_dir":"guide","_draft":false,"_partial":false,"_locale":"","title":"How does it works ?","description":"nitro-applicationinsights is simply a package which provides a plugin for nitro.","body":{"type":"root","children":[{"type":"element","tag":"h1","props":{"id":"how-does-it-works"},"children":[{"type":"text","value":"How does it works ?"}]},{"type":"element","tag":"p","props":{},"children":[{"type":"element","tag":"code","props":{"className":[]},"children":[{"type":"text","value":"nitro-applicationinsights"}]},{"type":"text","value":" is simply a package which provides a plugin for nitro."}]},{"type":"element","tag":"p","props":{},"children":[{"type":"text","value":"It setup the default client of "},{"type":"element","tag":"code","props":{"className":[]},"children":[{"type":"text","value":"applicationinsights"}]},{"type":"text","value":" on nitro start up. You can configure this by hooking into the "},{"type":"element","tag":"code","props":{"className":[]},"children":[{"type":"text","value":"applicationinsights:config"}]},{"type":"text","value":" hook of nitro."}]},{"type":"element","tag":"p","props":{},"children":[{"type":"text","value":"Since "},{"type":"element","tag":"code","props":{"className":[]},"children":[{"type":"text","value":"applicationinsights"}]},{"type":"text","value":" v3 uses Opentelemetry under the hood, this nitro plugin also run "},{"type":"element","tag":"code","props":{"className":[]},"children":[{"type":"text","value":"nitro-opentelemetry"}]},{"type":"text","value":"."}]},{"type":"element","tag":"h1","props":{"id":"automated-traces"},"children":[{"type":"text","value":"Automated traces"}]},{"type":"element","tag":"p","props":{},"children":[{"type":"text","value":"The "},{"type":"element","tag":"code","props":{"className":[]},"children":[{"type":"text","value":"nitro-opentelemetry"}]},{"type":"text","value":" plugin will automatically trace all your incoming and outgoing request from your Nitro server.\nThis means that you don't need to call "},{"type":"element","tag":"code","props":{"className":[]},"children":[{"type":"text","value":"defaultClient.trackDependency()"}]},{"type":"text","value":" yourself."}]}],"toc":{"title":"","searchDepth":2,"depth":2,"links":[]}},"_type":"markdown","_id":"content:1.guide:2.how-does-it-work.md","_source":"content","_file":"1.guide/2.how-does-it-work.md","_stem":"1.guide/2.how-does-it-work","_extension":"md"}